odoo/addons/ssi_psychology_testing/README.rst
odoo/addons/ssi_psychology_testing/__init__.py
odoo/addons/ssi_psychology_testing/__manifest__.py
odoo/addons/ssi_psychology_testing/menu.xml
odoo/addons/ssi_psychology_testing/data/approval_template_data.xml
odoo/addons/ssi_psychology_testing/data/ir_sequence_data.xml
odoo/addons/ssi_psychology_testing/data/policy_template_data.xml
odoo/addons/ssi_psychology_testing/data/sequence_template_data.xml
odoo/addons/ssi_psychology_testing/models/__init__.py
odoo/addons/ssi_psychology_testing/models/psychology_test.py
odoo/addons/ssi_psychology_testing/models/psychology_testing.py
odoo/addons/ssi_psychology_testing/models/psychology_testing_client.py
odoo/addons/ssi_psychology_testing/models/psychology_testing_observer.py
odoo/addons/ssi_psychology_testing/security/ir.model.access.csv
odoo/addons/ssi_psychology_testing/security/ir_module_category_data.xml
odoo/addons/ssi_psychology_testing/security/ir_rule_data.xml
odoo/addons/ssi_psychology_testing/security/res_group_data.xml
odoo/addons/ssi_psychology_testing/static/description/icon.png
odoo/addons/ssi_psychology_testing/views/psychology_test_views.xml
odoo/addons/ssi_psychology_testing/views/psychology_testing_views.xml
odoo14_addon_ssi_psychology_testing-14.0.1.3.0.dist-info/METADATA
odoo14_addon_ssi_psychology_testing-14.0.1.3.0.dist-info/WHEEL
odoo14_addon_ssi_psychology_testing-14.0.1.3.0.dist-info/top_level.txt
odoo14_addon_ssi_psychology_testing-14.0.1.3.0.dist-info/RECORD
